autodistill/__init__.py
autodistill/cli.py
autodistill/helpers.py
autodistill/models.csv
autodistill/registry.py
autodistill/utils.py
autodistill/classification/__init__.py
autodistill/classification/classification_base_model.py
autodistill/classification/classification_target_model.py
autodistill/core/__init__.py
autodistill/core/base_model.py
autodistill/core/composed_detection_model.py
autodistill/core/embedding_model.py
autodistill/core/embedding_ontology.py
autodistill/core/ontology.py
autodistill/core/target_model.py
autodistill/detection/__init__.py
autodistill/detection/caption_ontology.py
autodistill/detection/detection_base_model.py
autodistill/detection/detection_ontology.py
autodistill/detection/detection_target_model.py
autodistill/text_classification/__init__.py
autodistill/text_classification/text_classification_base_model.py
autodistill/text_classification/text_classification_ontology.py
autodistill/text_classification/text_classification_target_model.py
autodistill-0.1.29.dist-info/LICENSE
autodistill-0.1.29.dist-info/METADATA
autodistill-0.1.29.dist-info/WHEEL
autodistill-0.1.29.dist-info/entry_points.txt
autodistill-0.1.29.dist-info/top_level.txt
autodistill-0.1.29.dist-info/RECORD
