Metadata-Version: 2.1
Name: autodistill
Version: 0.1.29
Summary: Distill large foundational models into smaller, domain-specific models for deployment
Home-page: https://github.com/autodistill/autodistill
Author: Roboflow
Author-email: autodistill@roboflow.com
Classifier: Programming Language :: Python :: 3
Classifier: License :: OSI Approved :: Apache Software License
Classifier: Operating System :: OS Independent
Requires-Python: >=3.7
License-File: LICENSE
Requires-Dist: opencv-python>=4.6.0
Requires-Dist: supervision
Requires-Dist: tqdm
Requires-Dist: Pillow>=7.1.2
Requires-Dist: PyYAML>=5.3.1
Requires-Dist: click
Provides-Extra: dev
Requires-Dist: flake8; extra == "dev"
Requires-Dist: black==22.3.0; extra == "dev"
Requires-Dist: isort; extra == "dev"
Requires-Dist: twine; extra == "dev"
Requires-Dist: pytest; extra == "dev"
Requires-Dist: wheel; extra == "dev"
Requires-Dist: mkdocs-material; extra == "dev"
Requires-Dist: mkdocs; extra == "dev"
